subdomainradar/__init__.py
subdomainradar/api.py
subdomainradar-1.0.1.dist-info/LICENSE
subdomainradar-1.0.1.dist-info/METADATA
subdomainradar-1.0.1.dist-info/WHEEL
subdomainradar-1.0.1.dist-info/top_level.txt
subdomainradar-1.0.1.dist-info/RECORD
