Metadata-Version: 2.1
Name: subdomainradar
Version: 1.0.1
Summary: Python wrapper for SubdomainRadar.io API
Home-page: https://github.com/alexandrevandamme59/subdomainradar-python-wrapper
Author: Alexandre Vandamme
Author-email: alexandrevandammepro@gmail.com
Classifier: Programming Language :: Python :: 3
Classifier: Operating System :: OS Independent
License-File: LICENSE
Requires-Dist: requests>=2.0.0
